{"basics":{"name":"Emily Howerton","label":"Postdoctoral Research Associate","image":"img/prof_pic.jpg","email":"ehowerton@princeton.edu","phone":"(330) 990-1500"},"work":[{"name":"Department of Ecology and Evolutionary Biology and High Meadows Environmental Institute, Princeton University","position":"Postdoctoral Research Associate","startDate":"2024","endDate":""},{"name":"Department of Biology and Center for Infectious Disease Dynamics, Pennsylvania State University","position":"Graduate Research Assistant","startDate":"2018","endDate":"2023"}],"education":[{"institution":"Pennsylvania State University","location":"Pennsylvania, USA","area":"Biology","studyType":"PhD","startDate":"2018","endDate":"2023","highlights":"Dissertation: Quantitative Approaches to Improve the Management of Infectious Disease Outbreaks"},{"institution":"College of Wooster","location":"Ohio, USA","area":"Mathematics and Philosophy","studyType":"Bachelor of Arts","startDate":"2013","endDate":"2017","highlights":"Thesis: On Rationality and Morality: Three Kinds of Approaches"}]}